prenigma_automl/__init__.py
prenigma_automl/anomaly.py
prenigma_automl/arules.py
prenigma_automl/classification.py
prenigma_automl/clustering.py
prenigma_automl/datasets.py
prenigma_automl/nlp.py
prenigma_automl/preprocess.py
prenigma_automl/regression.py
prenigma_automl/utils.py
prenigma_automl-2.1.2.dist-info/LICENSE
prenigma_automl-2.1.2.dist-info/METADATA
prenigma_automl-2.1.2.dist-info/WHEEL
prenigma_automl-2.1.2.dist-info/top_level.txt
prenigma_automl-2.1.2.dist-info/RECORD
