Metadata-Version: 2.1
Name: prenigma-automl
Version: 2.1.2
Summary: prenigma_automl - An open source, low-code machine learning library.
Home-page: https://github.com/prenigma-auto-ml/prenigma_automl
Author: Prenigma
Author-email: hello@predapp.com
License: MIT
Platform: UNKNOWN
Classifier: License :: OSI Approved :: MIT License
Classifier: Programming Language :: Python :: 3.6
Classifier: Programming Language :: Python :: 3.7
Classifier: Programming Language :: Python :: 3.8
Requires-Dist: pandas
Requires-Dist: numpy (>=1.17)
Requires-Dist: seaborn
Requires-Dist: matplotlib
Requires-Dist: IPython
Requires-Dist: joblib
Requires-Dist: scikit-learn (>=0.23)
Requires-Dist: ipywidgets
Requires-Dist: yellowbrick (>=1.0.1)
Requires-Dist: xgboost (>=0.90)
Requires-Dist: lightgbm (>=2.3.1)
Requires-Dist: plotly (>=4.4.1)
Requires-Dist: wordcloud
Requires-Dist: textblob
Requires-Dist: cufflinks (>=0.17.0)
Requires-Dist: umap-learn
Requires-Dist: pyLDAvis
Requires-Dist: gensim
Requires-Dist: spacy
Requires-Dist: nltk
Requires-Dist: mlxtend
Requires-Dist: pyod
Requires-Dist: catboost (>=0.23.2)
Requires-Dist: pandas-profiling (>=2.8.0)
Requires-Dist: kmodes (>=0.10.1)
Requires-Dist: datefinder (>=0.7.0)
Requires-Dist: mlflow
Requires-Dist: imbalanced-learn (>=0.6.2)
